{
    "page_content": "Servizio casellario giudiziale. certificato del casellario giudiziale, fedina penale, carichi pendenti.",
    "metadata": {
      "comune": "NA",
      "date_orari": "{ \"2024-12-5\": [\"09.00-10.30\", \"15.00-16.00\"], \"2024-12-4\": [\"09.00-10.30\", \"14.30-16.00\"] }",
      "info": "\nCOS'E'\n\nIl certificato del casellario consente la conoscenza dei provvedimenti di condanna definitivi e di alcuni provvedimenti in materia civile e amministrativa a carico di un soggetto.\nIn particolare, l’ufficio del casellario giudiziale rilascia i seguenti certificati:\n\n    Certificato Generale: contiene i provvedimenti definitivi (sentenze irrevocabili) in materia penale, civile e amministrativa (riassume i certificati penale e civile).\n\n \nA COSA SERVE\n\nTali certificati sono richiesti per usi amministrativi di diversa natura ma anche per venire a conoscenza dei provvedimenti definitivi a proprio carico\nCHI PUO' RICHIEDERLO\n\nIl certificato può essere richiesto:\n\n    dall’interessato, da un suo delegato o difensore\n    dalle pubbliche amministrazioni e dai gestori di pubblici servizi, quando il certificato è necessario per l’espletamento delle loro funzioni\n    dall’autorità giudiziaria penale, che provvede direttamente alla sua acquisizione.\n\nCasi particolari:\n\n    Per i minorenni fino al compimento del sedicesimo anno di età la domanda va presentata dal genitore esercente la potestà genitoriale.\n    Per i minorenni oltre il sedicesimo anno di età, l'istanza può essere presentata dal diretto interessato. \n    Per gli interdetti la domanda va presentata dal tutore, che deve esibire il decreto di nomina.\n\nCOSA FARE PER RICHIEDERLO\n\nÈ necessario presentare la seguente documentazione:\n\n    Istanza\n    Documento di identità in corso di validità (nel caso di stranieri sprovvisti di passaporto si richiede copia del permesso di soggiorno)\n\nNel caso in cui la domanda sia presentata da un soggetto diverso dall’interessato occorre la delega e la fotocopia del documento del delegante e del delegato.\nA CHI DEVO RIVOLGERMI\n\nResponsabile del servizio: ---\n\nReferente per i servizi di certificazione richiesti alllo sportello:  ---\n\nReferente per i servizi di certificazione richiesti tramite posta elettronica: ---\n\nIndirizzo posta ordinaria: casellario.procura.napoli@giustizia.it\nIndirizzo PEC: casellario.procura.napoli@giustiziacert.it\nMODULISTICA\n\nDisponibile sia sul sito web della Procura che presso lo sportello casellario\n\n \n\n  \n\n \nVALIDITA'\n\n6 mesi dalla data del rilascio.\nDOVE DEVO RIVOLGERMI\n\nSportello Certificati - Nuovo Palazzo di Giustizia, ingresso via Grimaldi\n\n    Orario di apertura al pubblico: dal lunedì al venerdì dalle 8.30 alle 14.30\n    Orario accettazione istanze: dal lunedì al venerdì dalle 8.30 alle 12.30\n    Orario accettazione istanze urgenti: dal lunedì al venerdì dalle 8.30 alle 12.00\n\nLo sportello nel mese di agosto osserverà il seguente orario: dal lunedì al venerdì dallle 9.00 alle 12.00\nASSISTENZA LEGALE\n\nNon Necessaria\nCOSTI\n\nPer tutte le categorie di certificato occorre:\n\n    1 marca da bollo da 16,00 €\n    1 marca per diritti da 7,84 € se il certificato è richiesto con urgenza e consegna in giornata\n    1 marca da 3,92 € se il certificato è richiesto senza urgenza e consegna entro 4 giorni lavorativi\n    Il rilascio del certificato è gratuito quando è richiesto: per essere esibito nelle controversie di lavoro, previdenza ed assistenza obbligatoria (art. 10 L. 533/73)\n\nPer la visura non urgente non è previsto nessun costo.\nPer la visura urgente è previsto un costo di 3,92 € da corrispondere in marche amministrative.\nCOME FUNZIONA\n\nLa richiesta viene presentata allo sportello, specificando l’eventuale urgenza e corrispondendo le relative marche da bollo. L’ufficio verifica la corrispondenza dei dati e comunica la data di rilascio del certificato.\nÈ possibile prendere semplice visione di tutte le iscrizioni esistenti presso il casellario giudiziale a carico dell’interessato, medinate visura che non ha efficacia certificativa, quindi non può essere esibita per finalità amministrative o per ragioni di lavoro ma consente un controllo da parte dell’interessato dell’esattezza delle iscrizioni contenute nei registri del casellario, ai fini di eventuali richieste di rettifica. La visura può essere richiesta direttamente allo sportello. È necessario allegare fotocopia di un documento di identità in corso di validità. Nel caso in cui la visura sia richiesta da un delegato, è necessaria la delega e la fotocopia del documento di identità sia del richiedente che del delegato.\nNORMATIVA DI RIFERIMENTO\n\nArticoli 21, 23, 24, 25, 26, 28, 29, 33, 39 del D.P.R. n.313 del 14 Novembre 2002\n"
    }
  }